{"version":3,"kind":"Article","sha256":"685c3d34a1fdd6e4d204247e80b6769451b16328c0e0d45fd4b22d24f2663caf","slug":"final-project","location":"/final_project.md","dependencies":[],"frontmatter":{"title":"Final Project","downloads":[],"exports":[{"format":"md","filename":"final_project.md","url":"/build/final_project-1cd4087f0a6a14605b885d50e80521cc.md"}]},"mdast":{"type":"root","children":[{"type":"block","children":[{"type":"paragraph","position":{"start":{"line":6,"column":1},"end":{"line":6,"column":1}},"children":[{"type":"text","value":"Final Project ","position":{"start":{"line":6,"column":1},"end":{"line":6,"column":1}},"key":"Sbg2eWFEvz"},{"type":"link","url":"/build/CSE25_Project_Guidel-cb700385242540615079aa7e73b72f7f.pdf","position":{"start":{"line":6,"column":1},"end":{"line":6,"column":1}},"children":[{"type":"text","value":"guidelines","position":{"start":{"line":6,"column":1},"end":{"line":6,"column":1}},"key":"rRwhYmVoA3"}],"urlSource":"resources/CSE25_Project_Guidelines_release.pdf","static":true,"protocol":"file","key":"qicKmfj9c8"},{"type":"text","value":".","position":{"start":{"line":6,"column":1},"end":{"line":6,"column":1}},"key":"ZrdQjCsURh"}],"key":"MNKaWmPTFM"},{"type":"admonition","children":[{"type":"admonitionTitle","children":[{"type":"text","value":"📝 Teams Formation – Due: Thu, Feb 5, ","position":{"start":{"line":8,"column":1},"end":{"line":8,"column":1}},"key":"Qc3CWG0SCZ"},{"type":"strong","position":{"start":{"line":8,"column":1},"end":{"line":8,"column":1}},"children":[{"type":"text","value":"11:59 PM PT","position":{"start":{"line":8,"column":1},"end":{"line":8,"column":1}},"key":"Zi9i8VyQYf"}],"key":"XP6V19lon8"}],"key":"M7Mk3aVvnN"},{"type":"heading","depth":2,"position":{"start":{"line":15,"column":1},"end":{"line":15,"column":1}},"children":[{"type":"text","value":"Teams Formation","position":{"start":{"line":15,"column":1},"end":{"line":15,"column":1}},"key":"fTTVbdY5RD"}],"label":"teams-formation","identifier":"teams-formation","html_id":"teams-formation","key":"OYdDtxlp58"},{"type":"paragraph","position":{"start":{"line":17,"column":1},"end":{"line":17,"column":1}},"children":[{"type":"text","value":"Fill in one of the following: ","position":{"start":{"line":17,"column":1},"end":{"line":17,"column":1}},"key":"TfppWbFhVa"},{"type":"link","url":"https://docs.google.com/spreadsheets/d/11wSzBmQYf0C_DHbRLCRDeGJGreLiNq-HbNQJaInQ74E/edit?usp=sharing","position":{"start":{"line":17,"column":1},"end":{"line":17,"column":1}},"children":[{"type":"text","value":"Group Signup Sheet","position":{"start":{"line":17,"column":1},"end":{"line":17,"column":1}},"key":"xNyiiGhUlD"}],"urlSource":"https://docs.google.com/spreadsheets/d/11wSzBmQYf0C_DHbRLCRDeGJGreLiNq-HbNQJaInQ74E/edit?usp=sharing","key":"BC8BJZPBFV"},{"type":"text","value":" or ","position":{"start":{"line":17,"column":1},"end":{"line":17,"column":1}},"key":"qKxKdrCScF"},{"type":"link","url":"https://forms.gle/kR9RjnWQNpP4DBVG9","position":{"start":{"line":17,"column":1},"end":{"line":17,"column":1}},"children":[{"type":"text","value":"Random Assignment Form","position":{"start":{"line":17,"column":1},"end":{"line":17,"column":1}},"key":"pBGrwPb8m9"}],"urlSource":"https://forms.gle/kR9RjnWQNpP4DBVG9","key":"aBDfxhKwTr"},{"type":"text","value":".","position":{"start":{"line":17,"column":1},"end":{"line":17,"column":1}},"key":"PnOI16yOkZ"}],"key":"ZfpTNrB07T"},{"type":"paragraph","position":{"start":{"line":19,"column":1},"end":{"line":19,"column":1}},"children":[{"type":"text","value":"Groups will be finalized by Mon, Feb 9 with assigned mentor.","position":{"start":{"line":19,"column":1},"end":{"line":19,"column":1}},"key":"n30sS7QlG9"}],"key":"YPjkbWIrsP"},{"type":"paragraph","position":{"start":{"line":21,"column":1},"end":{"line":21,"column":1}},"children":[{"type":"strong","position":{"start":{"line":21,"column":1},"end":{"line":21,"column":1}},"children":[{"type":"text","value":"Grading","position":{"start":{"line":21,"column":1},"end":{"line":21,"column":1}},"key":"GsCUJCZHXI"}],"key":"Donwa37cMG"}],"key":"yxaXiVx72S"},{"type":"list","ordered":false,"spread":false,"position":{"start":{"line":23,"column":1},"end":{"line":24,"column":1}},"children":[{"type":"listItem","spread":true,"position":{"start":{"line":23,"column":1},"end":{"line":24,"column":1}},"children":[{"type":"paragraph","children":[{"type":"text","value":"5% of Final Project Grade","position":{"start":{"line":23,"column":1},"end":{"line":23,"column":1}},"key":"n8XifC4csj"}],"key":"paF42oSkGn"}],"key":"qJFZcVzSZC"}],"key":"YRTGfGdpqL"},{"type":"paragraph","position":{"start":{"line":25,"column":1},"end":{"line":25,"column":1}},"children":[{"type":"strong","position":{"start":{"line":25,"column":1},"end":{"line":25,"column":1}},"children":[{"type":"text","value":"Submission","position":{"start":{"line":25,"column":1},"end":{"line":25,"column":1}},"key":"iUq08ckmRU"}],"key":"V7ZhYdCazU"}],"key":"e156RHZChj"},{"type":"list","ordered":false,"spread":false,"position":{"start":{"line":27,"column":1},"end":{"line":28,"column":1}},"children":[{"type":"listItem","spread":true,"position":{"start":{"line":27,"column":1},"end":{"line":28,"column":1}},"children":[{"type":"paragraph","children":[{"type":"text","value":"Fill in either sheet or form by deadline.","position":{"start":{"line":27,"column":1},"end":{"line":27,"column":1}},"key":"r6bF7QtkgO"}],"key":"AOmZeEzCVW"}],"key":"nXMUH7chTx"}],"key":"iy55tWfAnI"},{"type":"paragraph","position":{"start":{"line":29,"column":1},"end":{"line":29,"column":1}},"children":[{"type":"strong","position":{"start":{"line":29,"column":1},"end":{"line":29,"column":1}},"children":[{"type":"text","value":"Late policy","position":{"start":{"line":29,"column":1},"end":{"line":29,"column":1}},"key":"cU7pmFHXev"}],"key":"HIce1m8jsm"}],"key":"Qc34nEAqqs"},{"type":"list","ordered":false,"spread":false,"position":{"start":{"line":31,"column":1},"end":{"line":31,"column":1}},"children":[{"type":"listItem","spread":true,"position":{"start":{"line":31,"column":1},"end":{"line":31,"column":1}},"children":[{"type":"paragraph","children":[{"type":"text","value":"Late submissions accepted but will be penalized.","position":{"start":{"line":31,"column":1},"end":{"line":31,"column":1}},"key":"D7z6qMMs3Z"}],"key":"nSKpfYqlsy"}],"key":"jsvMfxxUmT"}],"key":"LergENB4B1"}],"icon":false,"class":"danger dropdown","key":"GMuqRPVlQc"},{"type":"admonition","children":[{"type":"admonitionTitle","children":[{"type":"text","value":"📝 Project Proposal – Due: Thu, Feb 12, ","position":{"start":{"line":34,"column":1},"end":{"line":34,"column":1}},"key":"BTNOfewgmw"},{"type":"strong","position":{"start":{"line":34,"column":1},"end":{"line":34,"column":1}},"children":[{"type":"text","value":"11:59 PM PT","position":{"start":{"line":34,"column":1},"end":{"line":34,"column":1}},"key":"Ypr8L9Dpf1"}],"key":"aktOKmNQxL"}],"key":"Fd7g6Exc38"},{"type":"paragraph","position":{"start":{"line":39,"column":1},"end":{"line":39,"column":1}},"children":[{"type":"text","value":"(Project Proposal)=","position":{"start":{"line":39,"column":1},"end":{"line":39,"column":1}},"key":"GbOJgXjDHl"}],"key":"EVd174rtsT"},{"type":"heading","depth":2,"position":{"start":{"line":41,"column":1},"end":{"line":41,"column":1}},"children":[{"type":"text","value":"Project Proposal","position":{"start":{"line":41,"column":1},"end":{"line":41,"column":1}},"key":"JqHC2OSkyw"}],"identifier":"project-proposal","label":"Project Proposal","html_id":"project-proposal","implicit":true,"key":"vBz9u2xlIC"},{"type":"paragraph","position":{"start":{"line":43,"column":1},"end":{"line":43,"column":1}},"children":[{"type":"text","value":"TO BE ADDED","position":{"start":{"line":43,"column":1},"end":{"line":43,"column":1}},"key":"sede809RMH"}],"key":"oBTZh8EKMd"},{"type":"paragraph","position":{"start":{"line":45,"column":1},"end":{"line":45,"column":1}},"children":[{"type":"strong","position":{"start":{"line":45,"column":1},"end":{"line":45,"column":1}},"children":[{"type":"text","value":"Grading","position":{"start":{"line":45,"column":1},"end":{"line":45,"column":1}},"key":"fTBWaSpppT"}],"key":"VdT7nqpWEE"}],"key":"QRnlVS2R51"},{"type":"list","ordered":false,"spread":false,"position":{"start":{"line":47,"column":1},"end":{"line":48,"column":1}},"children":[{"type":"listItem","spread":true,"position":{"start":{"line":47,"column":1},"end":{"line":48,"column":1}},"children":[{"type":"paragraph","children":[{"type":"text","value":"5% of Final Project Grade","position":{"start":{"line":47,"column":1},"end":{"line":47,"column":1}},"key":"ogMAH3jHTs"}],"key":"hncdThB2bo"}],"key":"ZIUD6kEmQ2"}],"key":"b7FsgJz4lk"},{"type":"paragraph","position":{"start":{"line":49,"column":1},"end":{"line":49,"column":1}},"children":[{"type":"strong","position":{"start":{"line":49,"column":1},"end":{"line":49,"column":1}},"children":[{"type":"text","value":"Submission","position":{"start":{"line":49,"column":1},"end":{"line":49,"column":1}},"key":"LDtX7us0Fs"}],"key":"QTsE3qy7h0"}],"key":"Fe73spZyLv"},{"type":"list","ordered":false,"spread":false,"position":{"start":{"line":51,"column":1},"end":{"line":52,"column":1}},"children":[{"type":"listItem","spread":true,"position":{"start":{"line":51,"column":1},"end":{"line":52,"column":1}},"children":[{"type":"paragraph","children":[{"type":"text","value":"Gradescope by the designated deadline.","position":{"start":{"line":51,"column":1},"end":{"line":51,"column":1}},"key":"JRAFBuzalY"}],"key":"igElwAgXsE"}],"key":"O5m5YmVHVP"}],"key":"o2WfYv6LsY"},{"type":"paragraph","position":{"start":{"line":53,"column":1},"end":{"line":53,"column":1}},"children":[{"type":"strong","position":{"start":{"line":53,"column":1},"end":{"line":53,"column":1}},"children":[{"type":"text","value":"Late policy","position":{"start":{"line":53,"column":1},"end":{"line":53,"column":1}},"key":"mdjpEVHXVs"}],"key":"e7TyVh7LcR"}],"key":"ck8JezPdVO"},{"type":"list","ordered":false,"spread":false,"position":{"start":{"line":55,"column":1},"end":{"line":55,"column":1}},"children":[{"type":"listItem","spread":true,"position":{"start":{"line":55,"column":1},"end":{"line":55,"column":1}},"children":[{"type":"paragraph","children":[{"type":"text","value":"Late submissions accepted but will be penalized.","position":{"start":{"line":55,"column":1},"end":{"line":55,"column":1}},"key":"cAdPkDMEgd"}],"key":"OWATGHnvdv"}],"key":"hhoFheEwyx"}],"key":"YxI3KLQWDp"}],"icon":false,"class":"danger dropdown","key":"O2Ep2qwwfO"}],"key":"kK3vft5pBN"}],"key":"e2H4pMJfEs"},"references":{"cite":{"order":[],"data":{}}},"footer":{"navigation":{"prev":{"title":"Assignments","url":"/assignments","group":"CSE 25 - Intro to AI"},"next":{"title":"Syllabus","url":"/syllabus","group":"CSE 25 - Intro to AI"}}},"domain":"http://localhost:3000"}