{"version":3,"kind":"Article","sha256":"93f2b4a3615eb77673cbf87d8a35489484838f0e907c411b1e245f0811fccb5b","slug":"research","location":"/research.md","dependencies":[],"frontmatter":{"title":"Research","downloads":[],"exports":[{"format":"md","filename":"research.md","url":"/build/research-4d7761a66d1125e6191c09b56c83bd74.md"}]},"mdast":{"type":"root","children":[{"type":"block","children":[{"type":"heading","depth":2,"position":{"start":{"line":5,"column":1},"end":{"line":5,"column":1}},"children":[{"type":"text","value":"Study Overview","position":{"start":{"line":5,"column":1},"end":{"line":5,"column":1}},"key":"RWlFBRBYrm"}],"identifier":"study-overview","label":"Study Overview","html_id":"study-overview","implicit":true,"key":"y6uOpRZ0l9"},{"type":"paragraph","position":{"start":{"line":7,"column":1},"end":{"line":7,"column":1}},"children":[{"type":"text","value":"The instructor of this course, ","position":{"start":{"line":7,"column":1},"end":{"line":7,"column":1}},"key":"ovgC3o55Lu"},{"type":"strong","position":{"start":{"line":7,"column":1},"end":{"line":7,"column":1}},"children":[{"type":"text","value":"Dr. Trevor Bonjour (UC San Diego)","position":{"start":{"line":7,"column":1},"end":{"line":7,"column":1}},"key":"DT7ziwTCQu"}],"key":"gyC1pfnX8V"},{"type":"text","value":", is conducting a research study. The purpose of this study is to understand how students experience an introductory AI course that uses a neural-networks-first approach. The study examines:","position":{"start":{"line":7,"column":1},"end":{"line":7,"column":1}},"key":"BX6IchjfBM"}],"key":"AVae0VwkpG"},{"type":"list","ordered":false,"spread":false,"position":{"start":{"line":9,"column":1},"end":{"line":12,"column":1}},"children":[{"type":"listItem","spread":true,"position":{"start":{"line":9,"column":1},"end":{"line":9,"column":1}},"children":[{"type":"paragraph","children":[{"type":"text","value":"Perceptions of course difficulty, pacing, and workload","position":{"start":{"line":9,"column":1},"end":{"line":9,"column":1}},"key":"ftwfCSqLxp"}],"key":"lTgyWj9VZH"}],"key":"J5ap6kLa2n"},{"type":"listItem","spread":true,"position":{"start":{"line":10,"column":1},"end":{"line":10,"column":1}},"children":[{"type":"paragraph","children":[{"type":"text","value":"Confidence in learning AI concepts","position":{"start":{"line":10,"column":1},"end":{"line":10,"column":1}},"key":"mFEc12EXIq"}],"key":"GYFi1RNTHE"}],"key":"JAEAls8hFc"},{"type":"listItem","spread":true,"position":{"start":{"line":11,"column":1},"end":{"line":12,"column":1}},"children":[{"type":"paragraph","children":[{"type":"text","value":"How prior coding and mathematics experience relate to engagement and learning","position":{"start":{"line":11,"column":1},"end":{"line":11,"column":1}},"key":"WOtK6XZDPM"}],"key":"Gf08Ij7pkq"}],"key":"udbZLFKLGy"}],"key":"nnKF5VVOW5"},{"type":"thematicBreak","position":{"start":{"line":13,"column":1},"end":{"line":13,"column":1}},"key":"DtBDoVGo54"},{"type":"heading","depth":2,"position":{"start":{"line":15,"column":1},"end":{"line":15,"column":1}},"children":[{"type":"text","value":"Required Course Activities vs. Research Use of Data","position":{"start":{"line":15,"column":1},"end":{"line":15,"column":1}},"key":"yM3R7hn51c"}],"identifier":"required-course-activities-vs-research-use-of-data","label":"Required Course Activities vs. Research Use of Data","html_id":"required-course-activities-vs-research-use-of-data","implicit":true,"key":"s6VuaJvMwI"},{"type":"paragraph","position":{"start":{"line":17,"column":1},"end":{"line":17,"column":1}},"children":[{"type":"text","value":"The surveys are ","position":{"start":{"line":17,"column":1},"end":{"line":17,"column":1}},"key":"IPkez63Cd7"},{"type":"strong","position":{"start":{"line":17,"column":1},"end":{"line":17,"column":1}},"children":[{"type":"text","value":"required as part of the course","position":{"start":{"line":17,"column":1},"end":{"line":17,"column":1}},"key":"x4GI7sOIlV"}],"key":"AWdnPSzzCd"},{"type":"text","value":". However, ","position":{"start":{"line":17,"column":1},"end":{"line":17,"column":1}},"key":"RjMYx1x4Zx"},{"type":"strong","position":{"start":{"line":17,"column":1},"end":{"line":17,"column":1}},"children":[{"type":"text","value":"using this data for research is optional","position":{"start":{"line":17,"column":1},"end":{"line":17,"column":1}},"key":"Cwob2sRuhN"}],"key":"boYVfhDA57"},{"type":"text","value":".","position":{"start":{"line":17,"column":1},"end":{"line":17,"column":1}},"key":"zLCL73WZJi"}],"key":"KhwqIt8ZC9"},{"type":"list","ordered":false,"spread":false,"position":{"start":{"line":19,"column":1},"end":{"line":23,"column":1}},"children":[{"type":"listItem","spread":true,"position":{"start":{"line":19,"column":1},"end":{"line":19,"column":1}},"children":[{"type":"paragraph","children":[{"type":"text","value":"Completing surveys is required for the course","position":{"start":{"line":19,"column":1},"end":{"line":19,"column":1}},"key":"nwLL7YNVLT"}],"key":"iexh53SOfu"}],"key":"MzaYaNxhCf"},{"type":"listItem","spread":true,"position":{"start":{"line":20,"column":1},"end":{"line":20,"column":1}},"children":[{"type":"paragraph","children":[{"type":"text","value":"Allowing your data to be used for research is voluntary","position":{"start":{"line":20,"column":1},"end":{"line":20,"column":1}},"key":"laT8uKr1Eq"}],"key":"kAbskvZ7dK"}],"key":"gpaocggmPw"},{"type":"listItem","spread":true,"position":{"start":{"line":21,"column":1},"end":{"line":21,"column":1}},"children":[{"type":"paragraph","children":[{"type":"text","value":"If you opt out at any time, your data will ","position":{"start":{"line":21,"column":1},"end":{"line":21,"column":1}},"key":"f3pIB0OUbd"},{"type":"strong","position":{"start":{"line":21,"column":1},"end":{"line":21,"column":1}},"children":[{"type":"text","value":"not be used for research purposes","position":{"start":{"line":21,"column":1},"end":{"line":21,"column":1}},"key":"HrIRZMpPXQ"}],"key":"TUdgxtbF8C"}],"key":"yePJ1GtWhC"}],"key":"cdb5bHNn3O"},{"type":"listItem","spread":true,"position":{"start":{"line":22,"column":1},"end":{"line":23,"column":1}},"children":[{"type":"paragraph","children":[{"type":"text","value":"Opting out does ","position":{"start":{"line":22,"column":1},"end":{"line":22,"column":1}},"key":"rIVF0S7CJN"},{"type":"strong","position":{"start":{"line":22,"column":1},"end":{"line":22,"column":1}},"children":[{"type":"text","value":"not","position":{"start":{"line":22,"column":1},"end":{"line":22,"column":1}},"key":"VRzqQ4E7LI"}],"key":"g4LDJJ20KS"},{"type":"text","value":" affect your grade, standing, or access to course resources","position":{"start":{"line":22,"column":1},"end":{"line":22,"column":1}},"key":"EPzokeue4z"}],"key":"ugXPrdkvQs"}],"key":"xgESBm8heM"}],"key":"hj1tRO3JF3"},{"type":"thematicBreak","position":{"start":{"line":24,"column":1},"end":{"line":24,"column":1}},"key":"g0z6ZwzHPL"},{"type":"heading","depth":2,"position":{"start":{"line":26,"column":1},"end":{"line":26,"column":1}},"children":[{"type":"text","value":"What Participation May Involve","position":{"start":{"line":26,"column":1},"end":{"line":26,"column":1}},"key":"q2LU03kKOS"}],"identifier":"what-participation-may-involve","label":"What Participation May Involve","html_id":"what-participation-may-involve","implicit":true,"key":"Vf6VlhzJRn"},{"type":"paragraph","position":{"start":{"line":28,"column":1},"end":{"line":28,"column":1}},"children":[{"type":"text","value":"If you allow your data to be used for research, this may include:","position":{"start":{"line":28,"column":1},"end":{"line":28,"column":1}},"key":"yiUa8PpNxA"}],"key":"U5hpreJR7q"},{"type":"list","ordered":false,"spread":false,"position":{"start":{"line":30,"column":1},"end":{"line":34,"column":1}},"children":[{"type":"listItem","spread":true,"position":{"start":{"line":30,"column":1},"end":{"line":30,"column":1}},"children":[{"type":"paragraph","children":[{"type":"strong","position":{"start":{"line":30,"column":1},"end":{"line":30,"column":1}},"children":[{"type":"text","value":"Pre-course survey","position":{"start":{"line":30,"column":1},"end":{"line":30,"column":1}},"key":"cAFT5pNOWn"}],"key":"q3v1QFARtE"},{"type":"text","value":" (5–10 minutes)","position":{"start":{"line":30,"column":1},"end":{"line":30,"column":1}},"key":"TsP4WRjZTc"}],"key":"ACSuWiCrIn"}],"key":"L70BcebaqH"},{"type":"listItem","spread":true,"position":{"start":{"line":31,"column":1},"end":{"line":31,"column":1}},"children":[{"type":"paragraph","children":[{"type":"strong","position":{"start":{"line":31,"column":1},"end":{"line":31,"column":1}},"children":[{"type":"text","value":"Weekly “one-minute-paper” surveys","position":{"start":{"line":31,"column":1},"end":{"line":31,"column":1}},"key":"uuQFPN5Ooe"}],"key":"nBZpCKRda6"}],"key":"HZBn2WWCgp"}],"key":"sVgV8rokn5"},{"type":"listItem","spread":true,"position":{"start":{"line":32,"column":1},"end":{"line":32,"column":1}},"children":[{"type":"paragraph","children":[{"type":"strong","position":{"start":{"line":32,"column":1},"end":{"line":32,"column":1}},"children":[{"type":"text","value":"Post-course survey","position":{"start":{"line":32,"column":1},"end":{"line":32,"column":1}},"key":"K0eKtMfDlG"}],"key":"a3HpJqaz5F"},{"type":"text","value":" (5–10 minutes)","position":{"start":{"line":32,"column":1},"end":{"line":32,"column":1}},"key":"pap4BPj2Uo"}],"key":"poEwQABlNW"}],"key":"TL1KB3caKA"},{"type":"listItem","spread":true,"position":{"start":{"line":33,"column":1},"end":{"line":34,"column":1}},"children":[{"type":"paragraph","children":[{"type":"strong","position":{"start":{"line":33,"column":1},"end":{"line":33,"column":1}},"children":[{"type":"text","value":"Optional interview","position":{"start":{"line":33,"column":1},"end":{"line":33,"column":1}},"key":"tr3AjIpz97"}],"key":"E6JN6VoEos"},{"type":"text","value":": You may be invited to participate in a short, optional interview after completing the course. This interview will focus on your learning experience, perceptions, and reflections on the neural-networks-first approach used in the Introduction to Artificial Intelligence course. These interviews allow for more in-depth discussions and will allow students to share their experiences and perspectives in greater detail. With your permission, the interview will be audio recorded for transcription and analysis purposes.","position":{"start":{"line":33,"column":1},"end":{"line":33,"column":1}},"key":"IBQB3ArtJc"}],"key":"sq4cEkCPSp"}],"key":"c5EbRnRE0N"}],"key":"OlZuUhOSzO"},{"type":"paragraph","position":{"start":{"line":35,"column":1},"end":{"line":35,"column":1}},"children":[{"type":"text","value":"Participation lasts approximately the length of the course.","position":{"start":{"line":35,"column":1},"end":{"line":35,"column":1}},"key":"GTXHflgdyr"}],"key":"IiKkgcJJqD"},{"type":"thematicBreak","position":{"start":{"line":37,"column":1},"end":{"line":37,"column":1}},"key":"pmqh4xuOgy"},{"type":"heading","depth":2,"position":{"start":{"line":39,"column":1},"end":{"line":39,"column":1}},"children":[{"type":"text","value":"Eligibility","position":{"start":{"line":39,"column":1},"end":{"line":39,"column":1}},"key":"nLKCdLagnu"}],"identifier":"eligibility","label":"Eligibility","html_id":"eligibility","implicit":true,"key":"Vf8hyZMmvO"},{"type":"list","ordered":false,"spread":false,"position":{"start":{"line":41,"column":1},"end":{"line":44,"column":1}},"children":[{"type":"listItem","spread":true,"position":{"start":{"line":41,"column":1},"end":{"line":41,"column":1}},"children":[{"type":"paragraph","children":[{"type":"text","value":"This research includes only participants who are ","position":{"start":{"line":41,"column":1},"end":{"line":41,"column":1}},"key":"hZQi0S9AL7"},{"type":"strong","position":{"start":{"line":41,"column":1},"end":{"line":41,"column":1}},"children":[{"type":"text","value":"18 years of age or older","position":{"start":{"line":41,"column":1},"end":{"line":41,"column":1}},"key":"bBJ2XCavqJ"}],"key":"VFmvj3ZcxM"}],"key":"udqrq7pfMy"}],"key":"iiLx30VpzO"},{"type":"listItem","spread":true,"position":{"start":{"line":42,"column":1},"end":{"line":42,"column":1}},"children":[{"type":"paragraph","children":[{"type":"text","value":"If you are ","position":{"start":{"line":42,"column":1},"end":{"line":42,"column":1}},"key":"d5XnKv59Nd"},{"type":"strong","position":{"start":{"line":42,"column":1},"end":{"line":42,"column":1}},"children":[{"type":"text","value":"under 18","position":{"start":{"line":42,"column":1},"end":{"line":42,"column":1}},"key":"xdt54j4nA1"}],"key":"Aac2EZ4nTc"},{"type":"text","value":", your data will automatically ","position":{"start":{"line":42,"column":1},"end":{"line":42,"column":1}},"key":"PK2sOTtHtm"},{"type":"strong","position":{"start":{"line":42,"column":1},"end":{"line":42,"column":1}},"children":[{"type":"text","value":"not","position":{"start":{"line":42,"column":1},"end":{"line":42,"column":1}},"key":"STZY8pflDz"}],"key":"urIwp28m1Z"},{"type":"text","value":" be used for research","position":{"start":{"line":42,"column":1},"end":{"line":42,"column":1}},"key":"k35MM0NT8j"}],"key":"HXulBBXyrU"}],"key":"dFqliz1eno"},{"type":"listItem","spread":true,"position":{"start":{"line":43,"column":1},"end":{"line":44,"column":1}},"children":[{"type":"paragraph","children":[{"type":"text","value":"No action is required if you are under 18","position":{"start":{"line":43,"column":1},"end":{"line":43,"column":1}},"key":"axjtAgozEj"}],"key":"y0FUE2mho4"}],"key":"q79WQuaYNE"}],"key":"FtBlQbXyvd"},{"type":"thematicBreak","position":{"start":{"line":45,"column":1},"end":{"line":45,"column":1}},"key":"NKFVePgYdJ"},{"type":"heading","depth":2,"position":{"start":{"line":47,"column":1},"end":{"line":47,"column":1}},"children":[{"type":"text","value":"Voluntary Participation and Opting Out","position":{"start":{"line":47,"column":1},"end":{"line":47,"column":1}},"key":"KzqG1Isk4r"}],"identifier":"voluntary-participation-and-opting-out","label":"Voluntary Participation and Opting Out","html_id":"voluntary-participation-and-opting-out","implicit":true,"key":"ZSjl2Mo700"},{"type":"list","ordered":false,"spread":false,"position":{"start":{"line":49,"column":1},"end":{"line":53,"column":1}},"children":[{"type":"listItem","spread":true,"position":{"start":{"line":49,"column":1},"end":{"line":49,"column":1}},"children":[{"type":"paragraph","children":[{"type":"text","value":"Research participation is voluntary","position":{"start":{"line":49,"column":1},"end":{"line":49,"column":1}},"key":"p55nwwdpE5"}],"key":"sLC9fChD2d"}],"key":"gJFKSWA0DJ"},{"type":"listItem","spread":true,"position":{"start":{"line":50,"column":1},"end":{"line":50,"column":1}},"children":[{"type":"paragraph","children":[{"type":"text","value":"You may opt out at any time during the quarter","position":{"start":{"line":50,"column":1},"end":{"line":50,"column":1}},"key":"yctwlrQk2h"}],"key":"UFHlo82omr"}],"key":"DPAbl7aSP5"},{"type":"listItem","spread":true,"position":{"start":{"line":51,"column":1},"end":{"line":51,"column":1}},"children":[{"type":"paragraph","children":[{"type":"text","value":"You may skip any question","position":{"start":{"line":51,"column":1},"end":{"line":51,"column":1}},"key":"Zixn1Fycrp"}],"key":"DwNcS1bnTo"}],"key":"rqNiBEAXNj"},{"type":"listItem","spread":true,"position":{"start":{"line":52,"column":1},"end":{"line":53,"column":1}},"children":[{"type":"paragraph","children":[{"type":"text","value":"If you opt out, ","position":{"start":{"line":52,"column":1},"end":{"line":52,"column":1}},"key":"hvty6UqPbU"},{"type":"strong","position":{"start":{"line":52,"column":1},"end":{"line":52,"column":1}},"children":[{"type":"text","value":"all past and future course data will be excluded from the research dataset","position":{"start":{"line":52,"column":1},"end":{"line":52,"column":1}},"key":"D7NtlkkR5G"}],"key":"igQ3PtNc90"}],"key":"VyrA3bw4JP"}],"key":"IS3Z8wsInn"}],"key":"MFOXzsrxQ0"},{"type":"thematicBreak","position":{"start":{"line":54,"column":1},"end":{"line":54,"column":1}},"key":"zj9oWY8PAj"},{"type":"heading","depth":2,"position":{"start":{"line":56,"column":1},"end":{"line":56,"column":1}},"children":[{"type":"text","value":"Privacy and Confidentiality","position":{"start":{"line":56,"column":1},"end":{"line":56,"column":1}},"key":"veqisuEjiI"}],"identifier":"privacy-and-confidentiality","label":"Privacy and Confidentiality","html_id":"privacy-and-confidentiality","implicit":true,"key":"JZeHlc1qUr"},{"type":"paragraph","position":{"start":{"line":58,"column":1},"end":{"line":58,"column":1}},"children":[{"type":"text","value":"To protect your privacy:","position":{"start":{"line":58,"column":1},"end":{"line":58,"column":1}},"key":"atUAirvDtE"}],"key":"Kp3Yfc4Wvi"},{"type":"list","ordered":false,"spread":false,"position":{"start":{"line":60,"column":1},"end":{"line":64,"column":1}},"children":[{"type":"listItem","spread":true,"position":{"start":{"line":60,"column":1},"end":{"line":60,"column":1}},"children":[{"type":"paragraph","children":[{"type":"text","value":"Your responses will be anonymized using a unique participant ID.","position":{"start":{"line":60,"column":1},"end":{"line":60,"column":1}},"key":"lJbeHWvMV6"}],"key":"lao2C8bEvh"}],"key":"DtryC1Gd2a"},{"type":"listItem","spread":true,"position":{"start":{"line":61,"column":1},"end":{"line":61,"column":1}},"children":[{"type":"paragraph","children":[{"type":"text","value":"Any audio recordings will be stored securely on encrypted servers and accessed only by authorized research team members.","position":{"start":{"line":61,"column":1},"end":{"line":61,"column":1}},"key":"J3O1DHon7a"}],"key":"DueyKIEO7T"}],"key":"vytB4mgJGG"},{"type":"listItem","spread":true,"position":{"start":{"line":62,"column":1},"end":{"line":62,"column":1}},"children":[{"type":"paragraph","children":[{"type":"text","value":"Your responses will be shared only in de-identified, aggregated form (e.g., summary statistics) and will not contain any personally identifying information.","position":{"start":{"line":62,"column":1},"end":{"line":62,"column":1}},"key":"HmZgnUIBs8"}],"key":"gSviqB27EA"}],"key":"rhmChymLvU"},{"type":"listItem","spread":true,"position":{"start":{"line":63,"column":1},"end":{"line":64,"column":1}},"children":[{"type":"paragraph","children":[{"type":"text","value":"The de-identified data may be retained indefinitely and used for future research.","position":{"start":{"line":63,"column":1},"end":{"line":63,"column":1}},"key":"EurtwTWkIw"}],"key":"l1VKkortwt"}],"key":"hnYVABO16u"}],"key":"dwgZnd37rY"},{"type":"thematicBreak","position":{"start":{"line":65,"column":1},"end":{"line":65,"column":1}},"key":"aiNYUn9A8f"},{"type":"heading","depth":2,"position":{"start":{"line":67,"column":1},"end":{"line":67,"column":1}},"children":[{"type":"text","value":"How to Opt Out","position":{"start":{"line":67,"column":1},"end":{"line":67,"column":1}},"key":"JsB6DVvIHn"}],"identifier":"how-to-opt-out","label":"How to Opt Out","html_id":"how-to-opt-out","implicit":true,"key":"DGPKSEFJH0"},{"type":"paragraph","position":{"start":{"line":69,"column":1},"end":{"line":69,"column":1}},"children":[{"type":"text","value":"If you do not want your survey data used for research, complete the opt-out form below.","position":{"start":{"line":69,"column":1},"end":{"line":69,"column":1}},"key":"jCUHOBNWVA"}],"key":"ZyLGldUoJk"},{"type":"paragraph","position":{"start":{"line":71,"column":1},"end":{"line":71,"column":1}},"children":[{"type":"strong","position":{"start":{"line":71,"column":1},"end":{"line":71,"column":1}},"children":[{"type":"link","url":"https://forms.gle/1tLzjFAZsuPGnzr67","position":{"start":{"line":71,"column":1},"end":{"line":71,"column":1}},"children":[{"type":"text","value":"Opt-Out Form Link","position":{"start":{"line":71,"column":1},"end":{"line":71,"column":1}},"key":"vZ4jwgCP6i"}],"urlSource":"https://forms.gle/1tLzjFAZsuPGnzr67","key":"lj0VgdWFvy"}],"key":"AmOJculAew"}],"key":"TS3uut1Jh4"},{"type":"thematicBreak","position":{"start":{"line":73,"column":1},"end":{"line":73,"column":1}},"key":"AQPiEid12X"},{"type":"heading","depth":2,"position":{"start":{"line":75,"column":1},"end":{"line":75,"column":1}},"children":[{"type":"text","value":"Questions","position":{"start":{"line":75,"column":1},"end":{"line":75,"column":1}},"key":"lI85n9N4kt"}],"identifier":"questions","label":"Questions","html_id":"questions","implicit":true,"key":"H94sKMHGyU"},{"type":"paragraph","position":{"start":{"line":77,"column":1},"end":{"line":77,"column":1}},"children":[{"type":"text","value":"If you have questions about this study or your rights as a participant, please contact Trevor Bonjour: ","position":{"start":{"line":77,"column":1},"end":{"line":77,"column":1}},"key":"Qgcn8En8oY"},{"type":"link","url":"mailto:tbonjour@ucsd.edu","position":{"start":{"line":77,"column":1},"end":{"line":77,"column":1}},"children":[{"type":"text","value":"tbonjour@ucsd.edu","position":{"start":{"line":77,"column":1},"end":{"line":77,"column":1}},"key":"SbBjBGPVpo"}],"urlSource":"mailto:tbonjour@ucsd.edu","key":"mJuSiIk0iU"},{"type":"text","value":".","position":{"start":{"line":77,"column":1},"end":{"line":77,"column":1}},"key":"cRJxmILU9O"}],"key":"bw1XOhPufA"}],"key":"CTs95vc6Vh"}],"key":"x8PmTeKMZC"},"references":{"cite":{"order":[],"data":{}}},"footer":{"navigation":{"prev":{"title":"Course Staff","url":"/staff","group":"CSE 25 - Intro to AI"}}},"domain":"http://localhost:3000"}